modelhouse/__init__.py
modelhouse/main.py
modelhouse/utils.py
modelhouse/cli/__init__.py
modelhouse/cli/models.py
modelhouse/cli/storage.py
modelhouse/cli/version.py
modelhouse/loading/__init__.py
modelhouse/loading/loading.py
modelhouse/storage/__init__.py
modelhouse/storage/file_operations.py
modelhouse-0.1.4.dist-info/LICENSE
modelhouse-0.1.4.dist-info/METADATA
modelhouse-0.1.4.dist-info/WHEEL
modelhouse-0.1.4.dist-info/entry_points.txt
modelhouse-0.1.4.dist-info/top_level.txt
modelhouse-0.1.4.dist-info/RECORD
