Metadata-Version: 2.1
Name: modelhouse
Version: 0.1.4
Summary: Easy model distribution for inference.
Home-page: https://github.com/supersergiy/modelhouse
Author: Sergiy Popovych
Author-email: sergiy.popovich@gmail.com
License: UNKNOWN
Platform: UNKNOWN
License-File: LICENSE
Requires-Dist: numpy
